semantic_link_functions_validators-0.12.2.dist-info/licenses/LICENSE.txt
sempy_functions_validators/__init__.py
sempy_functions_validators/_validators.py
semantic_link_functions_validators-0.12.2.dist-info/METADATA
semantic_link_functions_validators-0.12.2.dist-info/WHEEL
semantic_link_functions_validators-0.12.2.dist-info/top_level.txt
semantic_link_functions_validators-0.12.2.dist-info/RECORD
