Metadata-Version: 2.4
Name: semantic-link-functions-validators
Version: 0.12.2
Summary: Semantic link functions for validators package. Enables validation of email addresses, credit card numbers, ... in FabricDataFrames.
Home-page: https://github.com/microsoft/semantic-link-functions
Author: Microsoft
Author-email: semanticdatascience@service.microsoft.com
License: MIT License
Platform: Microsoft Fabric
Classifier: Development Status :: 4 - Beta
Classifier: Intended Audience :: Developers
Classifier: License :: OSI Approved :: MIT License
Classifier: Programming Language :: Python :: 3.10
Requires-Python: >=3.10
License-File: LICENSE.txt
Requires-Dist: validators
Requires-Dist: semantic-link-sempy==0.12.2
Dynamic: author
Dynamic: author-email
Dynamic: classifier
Dynamic: description
Dynamic: description-content-type
Dynamic: home-page
Dynamic: license
Dynamic: license-file
Dynamic: platform
Dynamic: requires-dist
Dynamic: requires-python
Dynamic: summary
